MANIFEST.in
README.md
setup.py
distacc/__init__.py
distacc/credentials.py
distacc/post.py
distacc/test_1.py
distacc.egg-info/PKG-INFO
distacc.egg-info/SOURCES.txt
distacc.egg-info/dependency_links.txt
distacc.egg-info/requires.txt
distacc.egg-info/top_level.txt