Metadata-Version: 1.1
Name: distacc
Version: 0.0.1
Summary: Distributed object access
Home-page: https://github.com/niccokunzmann/distacc
Author: Nicco Kunzmann
Author-email: niccokunzmann@aol.com
License: MIT
Keywords: distributed game programming
Platform: UNKNOWN
Classifier: Development Status :: 3 - Alpha
Classifier: Intended Audience :: Developers
Classifier: License :: OSI Approved :: MIT License
Classifier: Topic :: Software Development :: Libraries :: Python Modules
Classifier: Topic :: Communications
Classifier: Topic :: Games/Entertainment
Classifier: Topic :: Internet
Classifier: Topic :: Software Development :: Object Brokering
